LICENSE
MANIFEST.in
README.md
setup.py
unrar_wrapper.py
tests/__init__.py
tests/functional_tests.sh
tests/test_unrar_wrapper.py
tests/__pycache__/test_unrar_wrapper.cpython-34.pyc
tests/testdata/functional/empty_dir.rar
tests/testdata/functional/file_without_dir.rar
tests/testdata/functional/files_without_dir.rar
tests/testdata/functional/listfiles1
tests/testdata/functional/listfiles2
tests/testdata/functional/many_dirs_many_files.rar
tests/testdata/functional/many_dirs_many_files_pass.rar
tests/testdata/functional/many_dirs_no_file.rar
tests/testdata/functional/one_dir_one_file.rar
tests/testdata/unit/emptylistfiles
tests/testdata/unit/listfiles1
tests/testdata/unit/listfiles2
unrar_wrapper.egg-info/PKG-INFO
unrar_wrapper.egg-info/SOURCES.txt
unrar_wrapper.egg-info/dependency_links.txt
unrar_wrapper.egg-info/entry_points.txt
unrar_wrapper.egg-info/top_level.txt