Metadata-Version: 1.1
Name: unrar-wrapper
Version: 1.0.0
Summary: Backwards compatibility between unar and unrar
Home-page: https://github.com/openSUSE/unrar_wrapper
Author: Kristyna Streitova
Author-email: kstreitova@suse.com
License: License :: OSI Approved :: GNU General Public License v3 (GPLv3)
Download-URL: https://github.com/openSUSE/unrar_wrapper
Keywords: unar unrar
Platform: Linux
Classifier: Development Status :: 5 - Production/Stable
Classifier: Intended Audience :: End Users/Desktop
Classifier: Programming Language :: Python
Classifier: Programming Language :: Python :: 3
Classifier: Programming Language :: Python :: 3.4
Classifier: Programming Language :: Python :: 3.5
Classifier: Programming Language :: Python :: 3.6
Classifier: Topic :: Utilities
Classifier: Topic :: System :: Archiving
